<?xml version="1.0" encoding="UTF-8"?>
<isp>
	<name>Israserv</name>
	<cname>israserv</cname>

	<dns1>192.115.0.100</dns1>
	<dns2>192.115.3.100</dns2>

	<support>
		<homepage>http://www.israserv.net.il</homepage>
		<tech>09-7428522</tech>
	</support>

	<email>
		<pop3>mail.israserv.net.il</pop3>
		<smtp>mail.israserv.net.il</smtp>
		<suffix>israserv.net.il</suffix>
	</email>

	<proxy>
		<manual>proxy.israserv.net.il:8080</manual>
	</proxy>

	<broadband>
		<gateway>
			<cable>
				<ip>192.117.195.250</ip>
				<remotename>192.117.195.250</remotename>
			</cable>
		</gateway>
		<usrsuffix type="adsl">@IIsraserv</usrsuffix>
	</broadband>
<!--
	<isdn>
		<server loc="The Center">03-6074000</server>
		<server loc="The North">04-8319800</server>
	</isdn>

	<dialup>
		<server loc="Jerusalem">02-6774444</server>
		<server loc="The Center">03-6941000</server>
		<server loc="The North">04-8319000</server>
		<server loc="The North 2">04-6952000</server>
		<server loc="The Sharon">09-7612000</server>
		<server loc="The South">08-9482900</server>
	</dialup>
-->
</isp>
